{
  "version": "6",
  "dialect": "sqlite",
  "id": "29f2c105-78d3-45be-be94-b1c59ef64466",
  "prevId": "00000000-0000-0000-0000-000000000000",
  "tables": {
    "campaign_logs": {
      "name": "campaign_logs",
      "columns": {
        "id": {
          "name": "id",
          "type": "text",
          "primaryKey": true,
          "notNull": true,
          "autoincrement": false
        },
        "campaign_id": {
          "name": "campaign_id",
          "type": "text",
          "primaryKey": false,
          "notNull": true,
          "autoincrement": false
        },
        "customer_id": {
          "name": "customer_id",
          "type": "text",
          "primaryKey": false,
          "notNull": true,
          "autoincrement": false
        },
        "message_type": {
          "name": "message_type",
          "type": "text",
          "primaryKey": false,
          "notNull": true,
          "autoincrement": false
        },
        "personalized_content": {
          "name": "personalized_content",
          "type": "text",
          "primaryKey": false,
          "notNull": false,
          "autoincrement": false
        },
        "status": {
          "name": "status",
          "type": "text",
          "primaryKey": false,
          "notNull": false,
          "autoincrement": false,
          "default": "'pending'"
        },
        "message_id": {
          "name": "message_id",
          "type": "text",
          "primaryKey": false,
          "notNull": false,
          "autoincrement": false
        },
        "sent_at": {
          "name": "sent_at",
          "type": "integer",
          "primaryKey": false,
          "notNull": false,
          "autoincrement": false
        },
        "delivered_at": {
          "name": "delivered_at",
          "type": "integer",
          "primaryKey": false,
          "notNull": false,
          "autoincrement": false
        },
        "opened_at": {
          "name": "opened_at",
          "type": "integer",
          "primaryKey": false,
          "notNull": false,
          "autoincrement": false
        },
        "clicked_at": {
          "name": "clicked_at",
          "type": "integer",
          "primaryKey": false,
          "notNull": false,
          "autoincrement": false
        },
        "error_message": {
          "name": "error_message",
          "type": "text",
          "primaryKey": false,
          "notNull": false,
          "autoincrement": false
        }
      },
      "indexes": {},
      "foreignKeys": {
        "campaign_logs_campaign_id_campaigns_id_fk": {
          "name": "campaign_logs_campaign_id_campaigns_id_fk",
          "tableFrom": "campaign_logs",
          "tableTo": "campaigns",
          "columnsFrom": [
            "campaign_id"
          ],
          "columnsTo": [
            "id"
          ],
          "onDelete": "cascade",
          "onUpdate": "no action"
        },
        "campaign_logs_customer_id_customers_id_fk": {
          "name": "campaign_logs_customer_id_customers_id_fk",
          "tableFrom": "campaign_logs",
          "tableTo": "customers",
          "columnsFrom": [
            "customer_id"
          ],
          "columnsTo": [
            "id"
          ],
          "onDelete": "cascade",
          "onUpdate": "no action"
        }
      },
      "compositePrimaryKeys": {},
      "uniqueConstraints": {},
      "checkConstraints": {}
    },
    "campaigns": {
      "name": "campaigns",
      "columns": {
        "id": {
          "name": "id",
          "type": "text",
          "primaryKey": true,
          "notNull": true,
          "autoincrement": false
        },
        "user_id": {
          "name": "user_id",
          "type": "text",
          "primaryKey": false,
          "notNull": true,
          "autoincrement": false
        },
        "name": {
          "name": "name",
          "type": "text",
          "primaryKey": false,
          "notNull": true,
          "autoincrement": false
        },
        "type": {
          "name": "type",
          "type": "text",
          "primaryKey": false,
          "notNull": true,
          "autoincrement": false
        },
        "status": {
          "name": "status",
          "type": "text",
          "primaryKey": false,
          "notNull": false,
          "autoincrement": false,
          "default": "'draft'"
        },
        "target_filter": {
          "name": "target_filter",
          "type": "text",
          "primaryKey": false,
          "notNull": false,
          "autoincrement": false
        },
        "email_subject": {
          "name": "email_subject",
          "type": "text",
          "primaryKey": false,
          "notNull": false,
          "autoincrement": false
        },
        "email_template": {
          "name": "email_template",
          "type": "text",
          "primaryKey": false,
          "notNull": false,
          "autoincrement": false
        },
        "sms_template": {
          "name": "sms_template",
          "type": "text",
          "primaryKey": false,
          "notNull": false,
          "autoincrement": false
        },
        "sent_count": {
          "name": "sent_count",
          "type": "integer",
          "primaryKey": false,
          "notNull": false,
          "autoincrement": false,
          "default": 0
        },
        "delivered_count": {
          "name": "delivered_count",
          "type": "integer",
          "primaryKey": false,
          "notNull": false,
          "autoincrement": false,
          "default": 0
        },
        "opened_count": {
          "name": "opened_count",
          "type": "integer",
          "primaryKey": false,
          "notNull": false,
          "autoincrement": false,
          "default": 0
        },
        "clicked_count": {
          "name": "clicked_count",
          "type": "integer",
          "primaryKey": false,
          "notNull": false,
          "autoincrement": false,
          "default": 0
        },
        "converted_count": {
          "name": "converted_count",
          "type": "integer",
          "primaryKey": false,
          "notNull": false,
          "autoincrement": false,
          "default": 0
        },
        "scheduled_at": {
          "name": "scheduled_at",
          "type": "integer",
          "primaryKey": false,
          "notNull": false,
          "autoincrement": false
        },
        "completed_at": {
          "name": "completed_at",
          "type": "integer",
          "primaryKey": false,
          "notNull": false,
          "autoincrement": false
        },
        "created_at": {
          "name": "created_at",
          "type": "integer",
          "primaryKey": false,
          "notNull": true,
          "autoincrement": false,
          "default": "(unixepoch())"
        }
      },
      "indexes": {},
      "foreignKeys": {
        "campaigns_user_id_users_id_fk": {
          "name": "campaigns_user_id_users_id_fk",
          "tableFrom": "campaigns",
          "tableTo": "users",
          "columnsFrom": [
            "user_id"
          ],
          "columnsTo": [
            "id"
          ],
          "onDelete": "cascade",
          "onUpdate": "no action"
        }
      },
      "compositePrimaryKeys": {},
      "uniqueConstraints": {},
      "checkConstraints": {}
    },
    "chat_history": {
      "name": "chat_history",
      "columns": {
        "id": {
          "name": "id",
          "type": "text",
          "primaryKey": true,
          "notNull": true,
          "autoincrement": false
        },
        "user_id": {
          "name": "user_id",
          "type": "text",
          "primaryKey": false,
          "notNull": true,
          "autoincrement": false
        },
        "user_message": {
          "name": "user_message",
          "type": "text",
          "primaryKey": false,
          "notNull": true,
          "autoincrement": false
        },
        "ai_response": {
          "name": "ai_response",
          "type": "text",
          "primaryKey": false,
          "notNull": true,
          "autoincrement": false
        },
        "context_used": {
          "name": "context_used",
          "type": "text",
          "primaryKey": false,
          "notNull": false,
          "autoincrement": false
        },
        "created_at": {
          "name": "created_at",
          "type": "integer",
          "primaryKey": false,
          "notNull": true,
          "autoincrement": false,
          "default": "(unixepoch())"
        }
      },
      "indexes": {},
      "foreignKeys": {
        "chat_history_user_id_users_id_fk": {
          "name": "chat_history_user_id_users_id_fk",
          "tableFrom": "chat_history",
          "tableTo": "users",
          "columnsFrom": [
            "user_id"
          ],
          "columnsTo": [
            "id"
          ],
          "onDelete": "cascade",
          "onUpdate": "no action"
        }
      },
      "compositePrimaryKeys": {},
      "uniqueConstraints": {},
      "checkConstraints": {}
    },
    "customer_events": {
      "name": "customer_events",
      "columns": {
        "id": {
          "name": "id",
          "type": "text",
          "primaryKey": true,
          "notNull": true,
          "autoincrement": false
        },
        "user_id": {
          "name": "user_id",
          "type": "text",
          "primaryKey": false,
          "notNull": true,
          "autoincrement": false
        },
        "customer_id": {
          "name": "customer_id",
          "type": "text",
          "primaryKey": false,
          "notNull": true,
          "autoincrement": false
        },
        "event_type": {
          "name": "event_type",
          "type": "text",
          "primaryKey": false,
          "notNull": true,
          "autoincrement": false
        },
        "event_data": {
          "name": "event_data",
          "type": "text",
          "primaryKey": false,
          "notNull": false,
          "autoincrement": false
        },
        "occurred_at": {
          "name": "occurred_at",
          "type": "integer",
          "primaryKey": false,
          "notNull": true,
          "autoincrement": false,
          "default": "(unixepoch())"
        }
      },
      "indexes": {},
      "foreignKeys": {
        "customer_events_user_id_users_id_fk": {
          "name": "customer_events_user_id_users_id_fk",
          "tableFrom": "customer_events",
          "tableTo": "users",
          "columnsFrom": [
            "user_id"
          ],
          "columnsTo": [
            "id"
          ],
          "onDelete": "cascade",
          "onUpdate": "no action"
        },
        "customer_events_customer_id_customers_id_fk": {
          "name": "customer_events_customer_id_customers_id_fk",
          "tableFrom": "customer_events",
          "tableTo": "customers",
          "columnsFrom": [
            "customer_id"
          ],
          "columnsTo": [
            "id"
          ],
          "onDelete": "cascade",
          "onUpdate": "no action"
        }
      },
      "compositePrimaryKeys": {},
      "uniqueConstraints": {},
      "checkConstraints": {}
    },
    "customers": {
      "name": "customers",
      "columns": {
        "id": {
          "name": "id",
          "type": "text",
          "primaryKey": true,
          "notNull": true,
          "autoincrement": false
        },
        "user_id": {
          "name": "user_id",
          "type": "text",
          "primaryKey": false,
          "notNull": true,
          "autoincrement": false
        },
        "external_id": {
          "name": "external_id",
          "type": "text",
          "primaryKey": false,
          "notNull": false,
          "autoincrement": false
        },
        "name": {
          "name": "name",
          "type": "text",
          "primaryKey": false,
          "notNull": true,
          "autoincrement": false
        },
        "email": {
          "name": "email",
          "type": "text",
          "primaryKey": false,
          "notNull": false,
          "autoincrement": false
        },
        "phone": {
          "name": "phone",
          "type": "text",
          "primaryKey": false,
          "notNull": false,
          "autoincrement": false
        },
        "company": {
          "name": "company",
          "type": "text",
          "primaryKey": false,
          "notNull": false,
          "autoincrement": false
        },
        "segment": {
          "name": "segment",
          "type": "text",
          "primaryKey": false,
          "notNull": false,
          "autoincrement": false
        },
        "last_activity_date": {
          "name": "last_activity_date",
          "type": "text",
          "primaryKey": false,
          "notNull": false,
          "autoincrement": false
        },
        "total_revenue": {
          "name": "total_revenue",
          "type": "real",
          "primaryKey": false,
          "notNull": false,
          "autoincrement": false,
          "default": 0
        },
        "support_tickets": {
          "name": "support_tickets",
          "type": "integer",
          "primaryKey": false,
          "notNull": false,
          "autoincrement": false,
          "default": 0
        },
        "churn_score": {
          "name": "churn_score",
          "type": "real",
          "primaryKey": false,
          "notNull": false,
          "autoincrement": false,
          "default": 0
        },
        "risk_level": {
          "name": "risk_level",
          "type": "text",
          "primaryKey": false,
          "notNull": false,
          "autoincrement": false,
          "default": "'low'"
        },
        "risk_factors": {
          "name": "risk_factors",
          "type": "text",
          "primaryKey": false,
          "notNull": false,
          "autoincrement": false
        },
        "metadata": {
          "name": "metadata",
          "type": "text",
          "primaryKey": false,
          "notNull": false,
          "autoincrement": false
        },
        "created_at": {
          "name": "created_at",
          "type": "integer",
          "primaryKey": false,
          "notNull": true,
          "autoincrement": false,
          "default": "(unixepoch())"
        },
        "updated_at": {
          "name": "updated_at",
          "type": "integer",
          "primaryKey": false,
          "notNull": true,
          "autoincrement": false,
          "default": "(unixepoch())"
        }
      },
      "indexes": {},
      "foreignKeys": {
        "customers_user_id_users_id_fk": {
          "name": "customers_user_id_users_id_fk",
          "tableFrom": "customers",
          "tableTo": "users",
          "columnsFrom": [
            "user_id"
          ],
          "columnsTo": [
            "id"
          ],
          "onDelete": "cascade",
          "onUpdate": "no action"
        }
      },
      "compositePrimaryKeys": {},
      "uniqueConstraints": {},
      "checkConstraints": {}
    },
    "file_uploads": {
      "name": "file_uploads",
      "columns": {
        "id": {
          "name": "id",
          "type": "text",
          "primaryKey": true,
          "notNull": true,
          "autoincrement": false
        },
        "user_id": {
          "name": "user_id",
          "type": "text",
          "primaryKey": false,
          "notNull": true,
          "autoincrement": false
        },
        "filename": {
          "name": "filename",
          "type": "text",
          "primaryKey": false,
          "notNull": true,
          "autoincrement": false
        },
        "file_type": {
          "name": "file_type",
          "type": "text",
          "primaryKey": false,
          "notNull": false,
          "autoincrement": false
        },
        "file_size_bytes": {
          "name": "file_size_bytes",
          "type": "integer",
          "primaryKey": false,
          "notNull": false,
          "autoincrement": false
        },
        "status": {
          "name": "status",
          "type": "text",
          "primaryKey": false,
          "notNull": false,
          "autoincrement": false,
          "default": "'pending'"
        },
        "records_imported": {
          "name": "records_imported",
          "type": "integer",
          "primaryKey": false,
          "notNull": false,
          "autoincrement": false,
          "default": 0
        },
        "records_failed": {
          "name": "records_failed",
          "type": "integer",
          "primaryKey": false,
          "notNull": false,
          "autoincrement": false,
          "default": 0
        },
        "validation_results": {
          "name": "validation_results",
          "type": "text",
          "primaryKey": false,
          "notNull": false,
          "autoincrement": false
        },
        "error_message": {
          "name": "error_message",
          "type": "text",
          "primaryKey": false,
          "notNull": false,
          "autoincrement": false
        },
        "created_at": {
          "name": "created_at",
          "type": "integer",
          "primaryKey": false,
          "notNull": true,
          "autoincrement": false,
          "default": "(unixepoch())"
        },
        "processed_at": {
          "name": "processed_at",
          "type": "integer",
          "primaryKey": false,
          "notNull": false,
          "autoincrement": false
        }
      },
      "indexes": {},
      "foreignKeys": {
        "file_uploads_user_id_users_id_fk": {
          "name": "file_uploads_user_id_users_id_fk",
          "tableFrom": "file_uploads",
          "tableTo": "users",
          "columnsFrom": [
            "user_id"
          ],
          "columnsTo": [
            "id"
          ],
          "onDelete": "cascade",
          "onUpdate": "no action"
        }
      },
      "compositePrimaryKeys": {},
      "uniqueConstraints": {},
      "checkConstraints": {}
    },
    "image_metadata": {
      "name": "image_metadata",
      "columns": {
        "id": {
          "name": "id",
          "type": "text",
          "primaryKey": true,
          "notNull": true,
          "autoincrement": false
        },
        "user_id": {
          "name": "user_id",
          "type": "text",
          "primaryKey": false,
          "notNull": true,
          "autoincrement": false
        },
        "google_drive_file_id": {
          "name": "google_drive_file_id",
          "type": "text",
          "primaryKey": false,
          "notNull": false,
          "autoincrement": false
        },
        "filename": {
          "name": "filename",
          "type": "text",
          "primaryKey": false,
          "notNull": true,
          "autoincrement": false
        },
        "mime_type": {
          "name": "mime_type",
          "type": "text",
          "primaryKey": false,
          "notNull": false,
          "autoincrement": false
        },
        "file_size": {
          "name": "file_size",
          "type": "integer",
          "primaryKey": false,
          "notNull": false,
          "autoincrement": false
        },
        "exif_data": {
          "name": "exif_data",
          "type": "text",
          "primaryKey": false,
          "notNull": false,
          "autoincrement": false
        },
        "analysis": {
          "name": "analysis",
          "type": "text",
          "primaryKey": false,
          "notNull": false,
          "autoincrement": false
        },
        "uploaded_at": {
          "name": "uploaded_at",
          "type": "integer",
          "primaryKey": false,
          "notNull": false,
          "autoincrement": false
        },
        "analyzed_at": {
          "name": "analyzed_at",
          "type": "integer",
          "primaryKey": false,
          "notNull": true,
          "autoincrement": false,
          "default": "(unixepoch())"
        }
      },
      "indexes": {},
      "foreignKeys": {
        "image_metadata_user_id_users_id_fk": {
          "name": "image_metadata_user_id_users_id_fk",
          "tableFrom": "image_metadata",
          "tableTo": "users",
          "columnsFrom": [
            "user_id"
          ],
          "columnsTo": [
            "id"
          ],
          "onDelete": "cascade",
          "onUpdate": "no action"
        }
      },
      "compositePrimaryKeys": {},
      "uniqueConstraints": {},
      "checkConstraints": {}
    },
    "reports": {
      "name": "reports",
      "columns": {
        "id": {
          "name": "id",
          "type": "text",
          "primaryKey": true,
          "notNull": true,
          "autoincrement": false
        },
        "user_id": {
          "name": "user_id",
          "type": "text",
          "primaryKey": false,
          "notNull": true,
          "autoincrement": false
        },
        "report_type": {
          "name": "report_type",
          "type": "text",
          "primaryKey": false,
          "notNull": true,
          "autoincrement": false
        },
        "title": {
          "name": "title",
          "type": "text",
          "primaryKey": false,
          "notNull": true,
          "autoincrement": false
        },
        "html_content": {
          "name": "html_content",
          "type": "text",
          "primaryKey": false,
          "notNull": false,
          "autoincrement": false
        },
        "report_data": {
          "name": "report_data",
          "type": "text",
          "primaryKey": false,
          "notNull": false,
          "autoincrement": false
        },
        "start_date": {
          "name": "start_date",
          "type": "integer",
          "primaryKey": false,
          "notNull": false,
          "autoincrement": false
        },
        "end_date": {
          "name": "end_date",
          "type": "integer",
          "primaryKey": false,
          "notNull": false,
          "autoincrement": false
        },
        "email_sent": {
          "name": "email_sent",
          "type": "integer",
          "primaryKey": false,
          "notNull": false,
          "autoincrement": false,
          "default": 0
        },
        "email_sent_at": {
          "name": "email_sent_at",
          "type": "integer",
          "primaryKey": false,
          "notNull": false,
          "autoincrement": false
        },
        "generated_at": {
          "name": "generated_at",
          "type": "integer",
          "primaryKey": false,
          "notNull": true,
          "autoincrement": false,
          "default": "(unixepoch())"
        }
      },
      "indexes": {},
      "foreignKeys": {
        "reports_user_id_users_id_fk": {
          "name": "reports_user_id_users_id_fk",
          "tableFrom": "reports",
          "tableTo": "users",
          "columnsFrom": [
            "user_id"
          ],
          "columnsTo": [
            "id"
          ],
          "onDelete": "cascade",
          "onUpdate": "no action"
        }
      },
      "compositePrimaryKeys": {},
      "uniqueConstraints": {},
      "checkConstraints": {}
    },
    "users": {
      "name": "users",
      "columns": {
        "id": {
          "name": "id",
          "type": "text",
          "primaryKey": true,
          "notNull": true,
          "autoincrement": false
        },
        "email": {
          "name": "email",
          "type": "text",
          "primaryKey": false,
          "notNull": true,
          "autoincrement": false
        },
        "password_hash": {
          "name": "password_hash",
          "type": "text",
          "primaryKey": false,
          "notNull": true,
          "autoincrement": false
        },
        "name": {
          "name": "name",
          "type": "text",
          "primaryKey": false,
          "notNull": false,
          "autoincrement": false
        },
        "avatar_url": {
          "name": "avatar_url",
          "type": "text",
          "primaryKey": false,
          "notNull": false,
          "autoincrement": false
        },
        "created_at": {
          "name": "created_at",
          "type": "integer",
          "primaryKey": false,
          "notNull": true,
          "autoincrement": false,
          "default": "(unixepoch())"
        }
      },
      "indexes": {
        "users_email_unique": {
          "name": "users_email_unique",
          "columns": [
            "email"
          ],
          "isUnique": true
        }
      },
      "foreignKeys": {},
      "compositePrimaryKeys": {},
      "uniqueConstraints": {},
      "checkConstraints": {}
    }
  },
  "views": {},
  "enums": {},
  "_meta": {
    "schemas": {},
    "tables": {},
    "columns": {}
  },
  "internal": {
    "indexes": {}
  }
}